fast_plscan/__init__.py
fast_plscan/_api.abi3.so
fast_plscan/_api.pyi
fast_plscan/_helpers.py
fast_plscan/api.py
fast_plscan/plots.py
fast_plscan/py.typed
fast_plscan/sklearn.py
fast_plscan.libs/libgomp-e985bcbb.so.1.0.0
fast_plscan-0.1.0.post2.dist-info/METADATA
fast_plscan-0.1.0.post2.dist-info/WHEEL
fast_plscan-0.1.0.post2.dist-info/RECORD
fast_plscan-0.1.0.post2.dist-info/licenses/LICENSE
fast_plscan-0.1.0.post2.dist-info/sboms/auditwheel.cdx.json
