Metadata-Version: 2.4
Name: fast-plscan
Version: 0.1.0.post2
Summary: A fast multi-core implementation of the PLSCAN clustering algorithm.
Keywords: density,cluster,clustering,hierarchical,persistent
Author-Email: Jelmer Bot <jelmerbot@gmail.com>
Maintainer-Email: Jelmer Bot <jelmerbot@gmail.com>
License-Expression: BSD-3-Clause
License-File: LICENSE
Classifier: Development Status :: 5 - Production/Stable
Classifier: Programming Language :: C++
Classifier: Programming Language :: Python :: 3
Classifier: Programming Language :: Python :: 3.10
Classifier: Programming Language :: Python :: 3.11
Classifier: Programming Language :: Python :: 3.12
Classifier: Programming Language :: Python :: 3.13
Classifier: Programming Language :: Python :: 3.14
Classifier: Operating System :: OS Independent
Classifier: Intended Audience :: Science/Research
Classifier: Intended Audience :: Developers
Classifier: Topic :: Scientific/Engineering
Classifier: Natural Language :: English
Project-URL: Documentation, https://fast-plscan.readthedocs.io
Project-URL: Homepage, https://github.com/JelmerBot/fast_plscan
Project-URL: Issues, https://github.com/JelmerBot/fast_plscan/issues
Requires-Python: >=3.10
Requires-Dist: numpy<3,>=2
Requires-Dist: scipy<2,>=1
Requires-Dist: matplotlib<4,>=3
Requires-Dist: scikit-learn<2,>=1.6
Provides-Extra: tests
Requires-Dist: pytest; extra == "tests"
Requires-Dist: networkx; extra == "tests"
Requires-Dist: pandas; extra == "tests"
Provides-Extra: docs
Requires-Dist: furo; extra == "docs"
Requires-Dist: sphinx; extra == "docs"
Requires-Dist: pandoc; extra == "docs"
Requires-Dist: nbsphinx; extra == "docs"
Requires-Dist: sphinx-copybutton; extra == "docs"
Requires-Dist: sphinx_autodoc_typehints; extra == "docs"
